Workbook

Sheet Transactions
A1: Date | B1: Transaction_ID | C1: Category | D1: Description | E1: Revenue ($) | F1: COGS ($) | G1: Marketing_Spend ($) | H1: Net_Profit ($) | I1: Notes
A2: 2026-01-10 | B2: TXN-201 | C2: Cloud Infrastructure | D2: AWS Reserved Instances - Q1 Batch | E2: 0 | F2: 4200 | G2: 0 | H2: =E2-F2-G2 | I2: Annual reservation, 3-year term
A3: 2026-01-18 | B3: TXN-202 | C3: SaaS Subscription | D3: Enterprise Tier — NovaTech Corp | E3: 8200 | F3: 1100 | G3: 600 | H3: =E3-F3-G3 | I3: Annual contract signed
A4: 2026-01-25 | B4: TXN-203 | C4: SaaS Subscription | D4: Professional Tier — Meridian Ltd | E4: 4500 | F4: 650 | G4: 350 | H4: =E4-F4-G4 | I4: Monthly billing
A5: 2026-02-05 | B5: TXN-204 | C5: Hardware | D5: GPU Workstations x4 — AI Dev Setup | E5: 0 | F5: 12000 | G5: 0 | H5: =E5-F5-G5 | I5: One-time capital expenditure
A6: 2026-02-14 | B6: TXN-205 | C6: SaaS Subscription | D6: Enterprise Tier — BrightEdge Inc | E6: 9500 | F6: 1200 | G6: 900 | H6: =E6-F6-G6 | I6: Expansion from Professional
A7: 2026-02-22 | B7: TXN-206 | C7: R&D | D7: OpenAI API Credits — Feb usage | E7: 0 | F7: 1800 | G7: 0 | H7: =E7-F7-G7 | I7: LLM inference costs
A8: 2026-03-03 | B8: TXN-207 | C8: Cloud Infrastructure | D8: GPU Cluster Rental — Model Training | E8: 0 | F8: 5800 | G8: 0 | H8: =E8-F8-G8 | I8: Needed for RAG pipeline
A9: 2026-03-12 | B9: TXN-208 | C9: SaaS Subscription | D9: Enterprise Tier — Apex Systems | E9: 11000 | F9: 1500 | G9: 2100 | H9: =E9-F9-G9 | I9: LinkedIn campaign lead
A10: 2026-03-20 | B10: TXN-209 | C10: SaaS Subscription | D10: Startup Tier — 3 new clients | E10: 3600 | F10: 540 | G10: 420 | H10: =E10-F10-G10 | I10: Self-serve signup via website
A11: 2026-03-28 | B11: TXN-210 | C11: R&D | D11: Pinecone Vector DB — Mar subscription | E11: 0 | F11: 480 | G11: 0 | H11: =E11-F11-G11 | I11: RAG infrastructure cost
A12: TOTALS | E12: =SUM(E2:E11) | F12: =SUM(F2:F11) | G12: =SUM(G2:G11) | H12: =SUM(H2:H11)

Sheet Monthly Summary
A1: Month | B1: Total Revenue ($) | C1: Total COGS ($) | D1: Marketing Spend ($) | E1: Net Profit ($) | F1: Gross Margin (%)
A2: January 2026 | B2: =SUMPRODUCT((TEXT(Transactions!A2:A11,"YYYY-MM")="2026-01")*Transactions!E2:E11) | C2: =SUMPRODUCT((TEXT(Transactions!A2:A11,"YYYY-MM")="2026-01")*Transactions!F2:F11) | D2: =SUMPRODUCT((TEXT(Transactions!A2:A11,"YYYY-MM")="2026-01")*Transactions!G2:G11) | E2: =B2-C2-D2 | F2: =IF(B2>0,(B2-C2)/B2*100,0)
A3: February 2026 | B3: =SUMPRODUCT((TEXT(Transactions!A2:A11,"YYYY-MM")="2026-02")*Transactions!E2:E11) | C3: =SUMPRODUCT((TEXT(Transactions!A2:A11,"YYYY-MM")="2026-02")*Transactions!F2:F11) | D3: =SUMPRODUCT((TEXT(Transactions!A2:A11,"YYYY-MM")="2026-02")*Transactions!G2:G11) | E3: =B3-C3-D3 | F3: =IF(B3>0,(B3-C3)/B3*100,0)
A4: March 2026 | B4: =SUMPRODUCT((TEXT(Transactions!A2:A11,"YYYY-MM")="2026-03")*Transactions!E2:E11) | C4: =SUMPRODUCT((TEXT(Transactions!A2:A11,"YYYY-MM")="2026-03")*Transactions!F2:F11) | D4: =SUMPRODUCT((TEXT(Transactions!A2:A11,"YYYY-MM")="2026-03")*Transactions!G2:G11) | E4: =B4-C4-D4 | F4: =IF(B4>0,(B4-C4)/B4*100,0)
